klient/__init__.py
klient/__main__.py
klient/admin.py
klient/consumer.py
klient/metrics.py
klient/producer.py
klient/relay.py
glean_klient-0.1.0.dist-info/METADATA
glean_klient-0.1.0.dist-info/WHEEL
glean_klient-0.1.0.dist-info/entry_points.txt
glean_klient-0.1.0.dist-info/top_level.txt
glean_klient-0.1.0.dist-info/RECORD
