Metadata-Version: 2.4
Name: glean-klient
Version: 0.1.0
Summary: Add your description here
Requires-Python: >=3.12
Requires-Dist: confluent-kafka>=2.12.0
Requires-Dist: click>=8.0.0
